mamba_lens/HookedMamba.py
mamba_lens/__init__.py
mamba_lens/input_dependent_hooks.py
mamba_lens-0.0.2.dist-info/LICENSE
mamba_lens-0.0.2.dist-info/METADATA
mamba_lens-0.0.2.dist-info/WHEEL
mamba_lens-0.0.2.dist-info/top_level.txt
mamba_lens-0.0.2.dist-info/RECORD
