Metadata-Version: 2.1
Name: mamba_lens
Version: 0.0.2
Summary: TransformerLens port for Mamba
Home-page: https://github.com/Phylliida/MambaLens.git
Author: Phylliida
Author-email: Danielle Ensign <phylliida.dev@gmail.com>
License: MIT License
Project-URL: Homepage, https://github.com/Phylliida/MambaLens.git
Project-URL: Issues, https://github.com/Phylliida/MambaLens/issues
Classifier: Operating System :: OS Independent
Requires-Python: >=3.6
License-File: LICENSE
Requires-Dist: transformer-lens
Requires-Dist: torch
Requires-Dist: einops
Requires-Dist: jaxtyping
